pybitget/__init__.py
pybitget/client.py
pybitget/enums.py
pybitget/exceptions.py
pybitget/stream.py
pybitget/utils.py
python_bitget-1.0.7.dist-info/METADATA
python_bitget-1.0.7.dist-info/WHEEL
python_bitget-1.0.7.dist-info/top_level.txt
python_bitget-1.0.7.dist-info/zip-safe
python_bitget-1.0.7.dist-info/RECORD
