Metadata-Version: 2.1
Name: python-bitget
Version: 1.0.7
Summary: bitget python wrapper with rest API, websocket API.
Home-page: https://github.com/cuongitl/python-bitget
Author: Cuongitl
Author-email: 
License: MIT
Keywords: Cuongitl bitget api restapi websocketapi example-python-bitget
Classifier: Intended Audience :: Developers
Classifier: License :: OSI Approved :: MIT License
Classifier: Operating System :: OS Independent
Classifier: Programming Language :: Python :: 3
Classifier: Programming Language :: Python
Classifier: Topic :: Software Development :: Libraries :: Python Modules
Requires-Python: >=3.6
Requires-Dist: requests
Requires-Dist: aiohttp
Requires-Dist: websockets
Requires-Dist: loguru
